defrostir/__init__.py
defrostir/__main__.py
defrostir-1.1.2.dist-info/LICENSE
defrostir-1.1.2.dist-info/METADATA
defrostir-1.1.2.dist-info/WHEEL
defrostir-1.1.2.dist-info/entry_points.txt
defrostir-1.1.2.dist-info/top_level.txt
defrostir-1.1.2.dist-info/RECORD
