Metadata-Version: 2.1
Name: defrostir
Version: 1.1.2
Summary: split broken icecast recordings into separate mp3s
Home-page: https://github.com/9001/defrost
Author: ed
Author-email: defrostir@ocv.me
License: MIT
Keywords: icecast internet radio stream ripping silence splitting
Classifier: License :: OSI Approved :: MIT License
Classifier: Development Status :: 5 - Production/Stable
Classifier: Environment :: Console
Classifier: Operating System :: Microsoft :: Windows
Classifier: Operating System :: POSIX :: Linux
Classifier: Operating System :: MacOS
Classifier: Topic :: Multimedia :: Sound/Audio
Classifier: Intended Audience :: End Users/Desktop
Classifier: Programming Language :: Python :: 2
Classifier: Programming Language :: Python :: 3
Requires-Python: >=2.7
License-File: LICENSE
Requires-Dist: mutagen
Requires-Dist: charset-normalizer
